Metadata-Version: 2.1
Name: froide-payment
Version: 0.0.3
Summary: Froide payment app
Home-page: https://github.com/okfde/froide-payment
Author: Stefan Wehrmeyer
Author-email: mail@stefanwehrmeyer.com
License: MIT
Platform: UNKNOWN
Classifier: Development Status :: 5 - Production/Stable
Classifier: Framework :: Django
Classifier: Intended Audience :: Developers
Classifier: License :: OSI Approved :: MIT License
Classifier: Operating System :: OS Independent
Classifier: Programming Language :: Python
Classifier: Programming Language :: Python :: 3
Classifier: Topic :: Utilities
Requires-Dist: django-payments
Requires-Dist: django-countries
Requires-Dist: django-prices
Requires-Dist: prices
Requires-Dist: stripe
